odoo8_addon_l10n_lu_ext-8.0.0.1.0.99.dev12-py2.7-nspkg.pth
odoo8_addon_l10n_lu_ext-8.0.0.1.0.99.dev12.dist-info/METADATA
odoo8_addon_l10n_lu_ext-8.0.0.1.0.99.dev12.dist-info/RECORD
odoo8_addon_l10n_lu_ext-8.0.0.1.0.99.dev12.dist-info/WHEEL
odoo8_addon_l10n_lu_ext-8.0.0.1.0.99.dev12.dist-info/namespace_packages.txt
odoo8_addon_l10n_lu_ext-8.0.0.1.0.99.dev12.dist-info/top_level.txt
odoo_addons/l10n_lu_ext/__init__.py
odoo_addons/l10n_lu_ext/__openerp__.py
odoo_addons/l10n_lu_ext/account_financial_report_view.xml
odoo_addons/l10n_lu_ext/i18n/am.po
odoo_addons/l10n_lu_ext/i18n/ar.po
odoo_addons/l10n_lu_ext/i18n/ca.po
odoo_addons/l10n_lu_ext/i18n/da.po
odoo_addons/l10n_lu_ext/i18n/de.po
odoo_addons/l10n_lu_ext/i18n/el_GR.po
odoo_addons/l10n_lu_ext/i18n/es.po
odoo_addons/l10n_lu_ext/i18n/es_ES.po
odoo_addons/l10n_lu_ext/i18n/es_MX.po
odoo_addons/l10n_lu_ext/i18n/fi.po
odoo_addons/l10n_lu_ext/i18n/fr.po
odoo_addons/l10n_lu_ext/i18n/fr_CA.po
odoo_addons/l10n_lu_ext/i18n/fr_FR.po
odoo_addons/l10n_lu_ext/i18n/hr.po
odoo_addons/l10n_lu_ext/i18n/hr_HR.po
odoo_addons/l10n_lu_ext/i18n/it.po
odoo_addons/l10n_lu_ext/i18n/l10n_lu_ext.pot
odoo_addons/l10n_lu_ext/i18n/nb.po
odoo_addons/l10n_lu_ext/i18n/nb_NO.po
odoo_addons/l10n_lu_ext/i18n/nl.po
odoo_addons/l10n_lu_ext/i18n/nl_BE.po
odoo_addons/l10n_lu_ext/i18n/nl_NL.po
odoo_addons/l10n_lu_ext/i18n/pt_BR.po
odoo_addons/l10n_lu_ext/i18n/ro.po
odoo_addons/l10n_lu_ext/i18n/sk.po
odoo_addons/l10n_lu_ext/i18n/sl.po
odoo_addons/l10n_lu_ext/i18n/tr.po
odoo_addons/l10n_lu_ext/i18n/zh_CN.po
odoo_addons/l10n_lu_ext/models/__init__.py
odoo_addons/l10n_lu_ext/models/res_company.py
odoo_addons/l10n_lu_ext/static/description/icon.png
odoo_addons/l10n_lu_ext/views/res_company.xml
